{"develop_doc_develop.md":"BojWda19","develop_doc_develop_format.md":"Ba-zXi7d","develop_doc_develop_guide.md":"C7jv06AC","develop_doc_docs.md":"C9Y1ds8j","develop_doc_env.md":"BC6lHtmx","develop_doc_log.md":"Dualpqcv","develop_doc_script_baas_thread.md":"Ct_zt3vO","develop_doc_script_config.md":"r6Tv0J9K","develop_doc_script_connection.md":"rqEWA-Ue","develop_doc_script_control.md":"BC7_d3oQ","develop_doc_script_device_operation.md":"BF_9HpIG","develop_doc_script_game_feature.md":"DkBYhJsH","develop_doc_script_image_compare.md":"CfMjHIl4","develop_doc_script_image_resource.md":"D9lKZ4x6","develop_doc_script_main.md":"Ct3NxPr5","develop_doc_script_nemu.md":"DkoTJhDz","develop_doc_script_ocr.md":"CTODmBey","develop_doc_script_screenshot.md":"CIj5vp3Q","i18n.md":"DcQEgwTM","index.md":"C2kHyNBw","markdown-examples.md":"nO0xbiBa","thanks.md":"CqCaP7OC","usage_doc_about.md":"-7gPNQSg","usage_doc_activity.md":"BQUk_Eus","usage_doc_api-examples.md":"BOlbb4hw","usage_doc_cli.md":"BCw0ZnN6","usage_doc_config.md":"Ddu9zGpq","usage_doc_destroyer.md":"CyTvazZk","usage_doc_downloads.md":"B_chnZM4","usage_doc_faq.md":"CzdRsvIS","usage_doc_features.md":"k9OLFe5C","usage_doc_guide.md":"CJBGMNN8","usage_doc_install_choose_platform.md":"I8aGkc3e","usage_doc_install_windows.md":"Cgo4WAu6","usage_doc_qq_group_regulation.md":"pcXxUWNd","usage_doc_report.md":"8_8L1mU0","usage_doc_update.md":"toTfPqLD"}
