{"develop_doc_develop.md":"BaeUeu2w","develop_doc_develop_format.md":"BnPcGwK1","develop_doc_develop_guide.md":"C88Jj8M_","develop_doc_docs.md":"D-yPoEr6","develop_doc_env.md":"CK3ybqxi","develop_doc_log.md":"hSeMCRsK","develop_doc_script_baas_thread.md":"Daspw1E2","develop_doc_script_config.md":"9i9PD4Bf","develop_doc_script_connection.md":"qqBPKMM9","develop_doc_script_control.md":"BP7zhOlU","develop_doc_script_device_operation.md":"DHajffev","develop_doc_script_game_feature.md":"BCbLQdC8","develop_doc_script_image_compare.md":"CqaRqwEU","develop_doc_script_image_resource.md":"YF9lX96G","develop_doc_script_main.md":"cXsPVDOO","develop_doc_script_nemu.md":"rYuYexju","develop_doc_script_ocr.md":"BI-lI0qY","develop_doc_script_screenshot.md":"CSZCMXMc","i18n.md":"BIOy3-A1","index.md":"C4MOINTw","markdown-examples.md":"DrM2KE5W","thanks.md":"i3DSLkF7","usage_doc_about.md":"B2l4Cxs5","usage_doc_activity.md":"Drxq8XUP","usage_doc_api-examples.md":"5NLfLcOi","usage_doc_cli.md":"JRU-Gnly","usage_doc_config.md":"BsViL4lv","usage_doc_destroyer.md":"CN-yLfxx","usage_doc_downloads.md":"vU_yFghE","usage_doc_faq.md":"TT2m1JIZ","usage_doc_features.md":"DO3qFLQR","usage_doc_guide.md":"BCagRVnN","usage_doc_install_choose_platform.md":"DYYahEXU","usage_doc_install_windows.md":"DkKr8hkg","usage_doc_qq_group_regulation.md":"DYQTYXQW","usage_doc_report.md":"qMrpcoU_","usage_doc_uninstall.md":"CN800SMs","usage_doc_update.md":"Cn9kSjVb"}
