{"develop_doc_develop.md":"QynsX8uk","develop_doc_develop_format.md":"CdYuf5Bo","develop_doc_develop_guide.md":"BswCi5jX","develop_doc_docs.md":"BSx2TQcS","develop_doc_env.md":"36khgS3O","develop_doc_log.md":"DhsIM2Dl","develop_doc_script_baas_thread.md":"CgS9JzbN","develop_doc_script_config.md":"1VKN1J5W","develop_doc_script_connection.md":"C9rneefg","develop_doc_script_control.md":"CpGO5WHz","develop_doc_script_device_operation.md":"Tf7MLys6","develop_doc_script_game_feature.md":"DZBFiGYs","develop_doc_script_image_compare.md":"3t5vjQRL","develop_doc_script_image_resource.md":"Dh1IlTHv","develop_doc_script_main.md":"CJ-ZMyDH","develop_doc_script_nemu.md":"jeAVtNmc","develop_doc_script_ocr.md":"BG7PR_kl","develop_doc_script_screenshot.md":"DE4lP9Ez","i18n.md":"C3iL-pm3","index.md":"MFlTO0KX","markdown-examples.md":"BqRaJNki","thanks.md":"B053JuaV","usage_doc_about.md":"Cb_qf43i","usage_doc_activity.md":"Bv8X5ULX","usage_doc_api-examples.md":"BlwB-0GK","usage_doc_cli.md":"Bi5Yzp4H","usage_doc_config.md":"BQkqsy0q","usage_doc_destroyer.md":"CLN_rnEr","usage_doc_downloads.md":"CtLGVYau","usage_doc_faq.md":"CLZZmJRj","usage_doc_features.md":"BjUiVKVE","usage_doc_guide.md":"LcF6B9_k","usage_doc_install_choose_platform.md":"BS0fpvUA","usage_doc_install_windows.md":"BhmZ7g5j","usage_doc_qq_group_regulation.md":"B9-dhlA3","usage_doc_report.md":"DCVC7b3Y","usage_doc_update.md":"HBMycVpJ"}
